genonets/__init__.py
genonets/accessibility_functions.py
genonets/analysis_handler.py
genonets/cmdl_handler.py
genonets/config.py
genonets/constants.py
genonets/epistasis_functions.py
genonets/errors.py
genonets/evolvability_functions.py
genonets/filters.py
genonets/graph_utils.py
genonets/interface.py
genonets/landscape_functions.py
genonets/overlap_functions.py
genonets/path_functions.py
genonets/peak_functions.py
genonets/reader.py
genonets/robustness_functions.py
genonets/sample/__init__.py
genonets/sample/config.cfg
genonets/sample/custom.py
genonets/sample/data/input.csv
genonets/sample/minimal.py
genonets/sample/parallel.py
genonets/sample/selective.py
genonets/sample/simple.py
genonets/seq_bit_impl.py
genonets/seq_bit_lib.py
genonets/structure_functions.py
genonets/utils.py
genonets/writer.py
genonets-2.0.dist-info/LICENSE
genonets-2.0.dist-info/WHEEL
genonets-2.0.dist-info/METADATA
genonets-2.0.dist-info/RECORD
