Metadata-Version: 2.1
Name: genonets
Version: 2.0
Summary: Framework for creating and analyzing genotype networks from.
Home-page: https://github.com/fkhalid/genonets
License: MIT
Keywords: genonets,genotype,phenotype,network
Author: Fahad Khalid
Author-email: genonets@outlook.com
Requires-Python: >=3.8,<4.0
Classifier: Development Status :: 5 - Production/Stable
Classifier: Environment :: Console
Classifier: Intended Audience :: Science/Research
Classifier: License :: OSI Approved :: MIT License
Classifier: Operating System :: OS Independent
Classifier: Programming Language :: Python :: 3
Classifier: Programming Language :: Python :: 3.8
Classifier: Topic :: Scientific/Engineering :: Bio-Informatics
Requires-Dist: numpy (>=1.19,<2.0)
Requires-Dist: python-igraph (==0.8.2)
Requires-Dist: tqdm (>=4.49.0,<5.0.0)
Project-URL: Documentation, https://genonets.readthedocs.io
Project-URL: Repository, https://github.com/fkhalid/genonets
